aioyoomoney/__init__.py
aioyoomoney/authorize.py
aioyoomoney/client.py
aioyoomoney/exceptions.py
aioyoomoney/globals.py
aioyoomoney/quickpay.py
aioyoomoney/utils.py
aioyoomoney/base/__init__.py
aioyoomoney/base/context_method.py
aioyoomoney/base/context_session.py
aioyoomoney/data_classes/__init__.py
aioyoomoney/data_classes/account.py
aioyoomoney/data_classes/balance_details.py
aioyoomoney/data_classes/card.py
aioyoomoney/data_classes/digital.py
aioyoomoney/data_classes/history.py
aioyoomoney/data_classes/operation.py
aioyoomoney/enums/__init__.py
aioyoomoney/enums/account.py
aioyoomoney/enums/history.py
aioyoomoney/enums/operation.py
aioyoomoney/enums/quickpay.py
aioyoomoney/methods/__init__.py
aioyoomoney/methods/account.py
aioyoomoney/methods/history.py
aioyoomoney/methods/operation_details.py
aioyoomoney_api-0.0.10.dist-info/METADATA
aioyoomoney_api-0.0.10.dist-info/WHEEL
aioyoomoney_api-0.0.10.dist-info/top_level.txt
aioyoomoney_api-0.0.10.dist-info/RECORD
