Metadata-Version: 2.1
Name: aioyoomoney-api
Version: 0.0.10
Summary: Async Yoomoney API
Project-URL: GitHub, https://github.com/paranoik1/aioyoomoney-api
Classifier: Programming Language :: Python :: 3
Classifier: License :: OSI Approved :: MIT License
Classifier: Operating System :: OS Independent
Requires-Python: >=3.11
Requires-Dist: aiohttp
Requires-Dist: requests
Requires-Dist: python-dateutil
